dlt_personio_source/__init__.py
dlt_personio_source/helpers.py
dlt_personio_source/loader.py
dlt_personio_source/personio_schema.yml
dlt_personio_source/personio_source.py
dlt_personio_source/personio_source_dummy.py
dlt_personio_source/personio_source_to_jsonl.py
dlt_personio_source/sample_data/absence_types.jsonl
dlt_personio_source/sample_data/absences.jsonl
dlt_personio_source/sample_data/attendances.jsonl
dlt_personio_source/sample_data/employees.jsonl
dlt_personio_source-0.0.46.dist-info/LICENSE
dlt_personio_source-0.0.46.dist-info/WHEEL
dlt_personio_source-0.0.46.dist-info/METADATA
dlt_personio_source-0.0.46.dist-info/RECORD
