Metadata-Version: 2.1
Name: dlt-personio-source
Version: 0.0.46
Summary: 
License: apache
Author: Adrian Brudaru
Author-email: adrian@scalevector.ai
Requires-Python: >=3.8,<4.0
Classifier: License :: Other/Proprietary License
Classifier: Programming Language :: Python :: 3
Classifier: Programming Language :: Python :: 3.10
Classifier: Programming Language :: Python :: 3.8
Classifier: Programming Language :: Python :: 3.9
Requires-Dist: google-cloud-bigquery
Requires-Dist: personio-py (>=0.2.1,<0.3.0)
Requires-Dist: python-dlt
